st_audio_spectrogram/__init__.py
st_audio_spectrogram/example.py
st_audio_spectrogram/frontend/build/asset-manifest.json
st_audio_spectrogram/frontend/build/bootstrap.min.css
st_audio_spectrogram/frontend/build/demo.wav
st_audio_spectrogram/frontend/build/index.html
st_audio_spectrogram/frontend/build/static/css/main.fc5c2c69.css
st_audio_spectrogram/frontend/build/static/css/main.fc5c2c69.css.map
st_audio_spectrogram/frontend/build/static/js/main.785a89f2.js
st_audio_spectrogram/frontend/build/static/js/main.785a89f2.js.LICENSE.txt
st_audio_spectrogram/frontend/build/static/js/main.785a89f2.js.map
st_audio_spectrogram-0.0.5.dist-info/LICENSE
st_audio_spectrogram-0.0.5.dist-info/METADATA
st_audio_spectrogram-0.0.5.dist-info/WHEEL
st_audio_spectrogram-0.0.5.dist-info/top_level.txt
st_audio_spectrogram-0.0.5.dist-info/RECORD
