Metadata-Version: 2.1
Name: st_audio_spectrogram
Version: 0.0.5
Summary: Streamlit component to view wavforms and spectrogram
Home-page: 
Author: Douglas Blank
Author-email: doug@comet.com
Requires-Python: >=3.7
License-File: LICENSE
Requires-Dist: streamlit >=0.63
